dist/ka_ut_air-2023.2.1-py3-none-any.whl
dist/ka_ut_air-2023.2.1.tar.gz
ka_ut_air/__init__.py
ka_ut_air/__version__.py
ka_ut_air/tpl.py
ka_ut_air/data/__init__.py
ka_ut_air/docs/ERRORS.txt
ka_ut_air/docs/conf.py
ka_ut_air/docs/index.rst
ka_ut_air/docs/make.bat
ka_ut_air/docs/_build/doctrees/environment.pickle
ka_ut_air/docs/_build/doctrees/index.doctree
ka_ut_air/docs/_build/html/genindex.html
ka_ut_air/docs/_build/html/index.html
ka_ut_air/docs/_build/html/objects.inv
ka_ut_air/docs/_build/html/search.html
ka_ut_air/docs/_build/html/searchindex.js
ka_ut_air/docs/_build/html/_sources/index.rst.txt
ka_ut_air/docs/_build/html/_static/alabaster.css
ka_ut_air/docs/_build/html/_static/basic.css
ka_ut_air/docs/_build/html/_static/custom.css
ka_ut_air/docs/_build/html/_static/doctools.js
ka_ut_air/docs/_build/html/_static/documentation_options.js
ka_ut_air/docs/_build/html/_static/file.png
ka_ut_air/docs/_build/html/_static/language_data.js
ka_ut_air/docs/_build/html/_static/minus.png
ka_ut_air/docs/_build/html/_static/plus.png
ka_ut_air/docs/_build/html/_static/pygments.css
ka_ut_air/docs/_build/html/_static/searchtools.js
ka_ut_air/docs/_build/html/_static/sphinx_highlight.js
ka_ut_air/docs/_build/man/controlmapplications.1
ka_ut_air-2023.2.1.dist-info/LICENSE.txt
ka_ut_air-2023.2.1.dist-info/METADATA
ka_ut_air-2023.2.1.dist-info/WHEEL
ka_ut_air-2023.2.1.dist-info/top_level.txt
ka_ut_air-2023.2.1.dist-info/RECORD
